quantum_gateway.py
quantum_gateway-0.0.8.dist-info/LICENSE.txt
quantum_gateway-0.0.8.dist-info/METADATA
quantum_gateway-0.0.8.dist-info/WHEEL
quantum_gateway-0.0.8.dist-info/top_level.txt
quantum_gateway-0.0.8.dist-info/RECORD
