Metadata-Version: 2.1
Name: quantum-gateway
Version: 0.0.8
Summary: Query a Quantum Gateway
Home-page: https://github.com/cisasteelersfan/quantum_gateway
Author: Colby Rome
Author-email: colbyrome@gmail.com
Classifier: Programming Language :: Python :: 3
Classifier: License :: OSI Approved :: MIT License
Classifier: Operating System :: OS Independent
License-File: LICENSE.txt
